LICENSE
README.md
setup.py
DjangoStateKeeper/__init__.py
DjangoStateKeeper/asgi.py
DjangoStateKeeper/settings.py
DjangoStateKeeper/urls.py
DjangoStateKeeper/wsgi.py
django_state_keeper/__init__.py
django_state_keeper/admin.py
django_state_keeper/apps.py
django_state_keeper/auto_backup_model.py
django_state_keeper/loading_backup_model.py
django_state_keeper/logging_utils.py
django_state_keeper/packaging_backup_model.py
django_state_keeper/urls.py
django_state_keeper/views.py
django_state_keeper.egg-info/PKG-INFO
django_state_keeper.egg-info/SOURCES.txt
django_state_keeper.egg-info/dependency_links.txt
django_state_keeper.egg-info/requires.txt
django_state_keeper.egg-info/top_level.txt
django_state_keeper/migrations/0001_initial.py
django_state_keeper/migrations/0002_delete_backupupload_and_more.py
django_state_keeper/migrations/0003_backupupload.py
django_state_keeper/migrations/__init__.py